juno/__init__.py
juno/__main__.py
juno/ast.py
juno/interpreter.py
juno/jit.py
juno/lexer.py
juno/parser.py
juno/runtime.py
juno/tools/__init__.py
juno/tools/debugger.py
juno/tools/formatter.py
juno/tools/linter.py
juno/tools/package.py
juno_lang-0.1.0.dist-info/licenses/LICENSE
tests/__init__.py
tests/run_tests.py
tests/test_lexer.py
juno_lang-0.1.0.dist-info/METADATA
juno_lang-0.1.0.dist-info/WHEEL
juno_lang-0.1.0.dist-info/entry_points.txt
juno_lang-0.1.0.dist-info/top_level.txt
juno_lang-0.1.0.dist-info/RECORD
